xaal/__init__.py
xaal/meross/__init__.py
xaal/meross/__main__.py
xaal/meross/bindings.py
xaal/meross/gw.py
xaal_meross-0.3.1.dist-info/METADATA
xaal_meross-0.3.1.dist-info/WHEEL
xaal_meross-0.3.1.dist-info/top_level.txt
xaal_meross-0.3.1.dist-info/RECORD
